MANIFEST.in
README.rst
setup.py
django_user_extension.egg-info/PKG-INFO
django_user_extension.egg-info/SOURCES.txt
django_user_extension.egg-info/dependency_links.txt
django_user_extension.egg-info/not-zip-safe
django_user_extension.egg-info/requires.txt
django_user_extension.egg-info/top_level.txt
user_extension/__init__.py
user_extension/admin.py
user_extension/backends.py
user_extension/models.py