Metadata-Version: 1.0
Name: django-user-extension
Version: 1.0.0
Summary: Subclass the Django User model to your heart's delight.
Home-page: http://bitbucket.org/dbinit/django-user-extension/
Author: David Bennett
Author-email: david@dbinit.com
License: UNKNOWN
Platform: UNKNOWN
Classifier: Development Status :: 4 - Beta
Classifier: Environment :: Web Environment
Classifier: Framework :: Django
Classifier: Intended Audience :: Developers
Classifier: License :: OSI Approved :: MIT License
Classifier: Operating System :: OS Independent
Classifier: Programming Language :: Python
Classifier: Topic :: Software Development :: Libraries :: Python Modules
Classifier: Topic :: Utilities
